nautobot_auto_provisioner/__init__.py
nautobot_auto_provisioner/app-config-schema.json
nautobot_auto_provisioner/jobs/__init__.py
nautobot_auto_provisioner/jobs/baseline_existing_device.py
nautobot_auto_provisioner/jobs/provision_new_device.py
nautobot_auto_provisioner/jobs/replace_existing_device.py
nautobot_auto_provisioner/tests/__init__.py
nautobot_auto_provisioner/urls.py
nautobot_auto_provisioner/utils/__init__.py
nautobot_auto_provisioner/utils/config_pusher.py
nautobot_auto_provisioner/utils/credentials_handler.py
nautobot_auto_provisioner/utils/git_repo_path_resolver.py
nautobot_auto_provisioner-2.0.0.dist-info/METADATA
nautobot_auto_provisioner-2.0.0.dist-info/WHEEL
nautobot_auto_provisioner-2.0.0.dist-info/licenses/LICENSE
nautobot_auto_provisioner-2.0.0.dist-info/RECORD
