Metadata-Version: 2.4
Name: nautobot-auto-provisioner
Version: 2.0.0
Summary: Easily provision new or existing devices based on pre-defined intended configurations.
License: Apache-2.0
License-File: LICENSE
Keywords: nautobot,nautobot-app,nautobot-plugin
Author: Dwayne Camacho
Author-email: dwayne.a.camacho@gmail.com
Requires-Python: >=3.10,<3.14
Classifier: Development Status :: 5 - Production/Stable
Classifier: Intended Audience :: Developers
Classifier: License :: OSI Approved :: Apache Software License
Classifier: Programming Language :: Python :: 3
Classifier: Programming Language :: Python :: 3.10
Classifier: Programming Language :: Python :: 3.11
Classifier: Programming Language :: Python :: 3.12
Classifier: Programming Language :: Python :: 3.13
Provides-Extra: all
Requires-Dist: nautobot (>=3.0.0,<4.0.0)
Project-URL: Documentation, https://docs.nautobot.com/projects/nautobot-auto-provisioner/en/latest/
Project-URL: Homepage, https://github.com/d-camacho/nautobot-auto-provisioner
Project-URL: Repository, https://github.com/d-camacho/nautobot-auto-provisioner
